<?xml version="1.0" encoding="UTF-8"?>
<PAGE width="467.717" height="680.315" number="5" id="p5"><MEDIABOX x1="0" y1="0" x2="467.717" y2="680.315"/><CROPBOX x1="0" y1="0" x2="467.717" y2="680.315"/><BLEEDBOX x1="0" y1="0" x2="467.717" y2="680.315"/><ARTBOX x1="0" y1="0" x2="467.717" y2="680.315"/><TRIMBOX x1="0" y1="0" x2="467.717" y2="680.315"/><TEXT width="195.995" height="11.9225" id="p5_t1" x="135.863" y="32.1917"><TOKEN sid="p5_s1941" id="p5_w1" font-name="AGaramondPro" symbolic="yes" bold="no" italic="yes" font-size="9.5" font-color="#231f1f" rotation="0" angle="0" x="135.863" y="32.1917" base="40.9032" width="26.543" height="11.9225">Further</TOKEN><TOKEN sid="p5_s1942" id="p5_w2" font-name="agaramondpro" symbolic="yes" bold="no" italic="yes" font-size="9.5" font-color="#231f1f" rotation="0" angle="0" x="164.781" y="32.1917" base="40.9032" width="23.446" height="11.9225">records</TOKEN><TOKEN sid="p5_s1943" id="p5_w3" font-name="agaramondpro" symbolic="yes" bold="no" italic="yes" font-size="9.5" font-color="#231f1f" rotation="0" angle="0" x="190.602" y="32.1917" base="40.9032" width="6.3365" height="11.9225">of</TOKEN><TOKEN sid="p5_s1944" id="p5_w4" font-name="agaramondpro" symbolic="yes" bold="no" italic="yes" font-size="9.5" font-color="#231f1f" rotation="0" angle="0" x="199.313" y="32.1917" base="40.9032" width="39.3205" height="11.9225">non-cryptic</TOKEN><TOKEN sid="p5_s1945" id="p5_w5" font-name="agaramondpro" symbolic="yes" bold="no" italic="yes" font-size="9.5" font-color="#231f1f" rotation="0" angle="0" x="241.009" y="32.1917" base="40.9032" width="16.264" height="11.9225">New</TOKEN><TOKEN sid="p5_s1946" id="p5_w6" font-name="agaramondpro" symbolic="yes" bold="no" italic="yes" font-size="9.5" font-color="#231f1f" rotation="0" angle="0" x="259.648" y="32.1917" base="40.9032" width="28.975" height="11.9225">Zealand</TOKEN><TOKEN sid="p5_s1947" id="p5_w7" font-name="agaramondpro" symbolic="yes" bold="no" italic="yes" font-size="9.5" font-color="#231f1f" rotation="0" angle="0" x="290.998" y="32.1917" base="40.9032" width="40.8595" height="11.9225">earthworms</TOKEN></TEXT><TEXT width="9.5" height="12.0745" id="p5_t2" x="405.777" y="32.1917"><TOKEN sid="p5_s1948" id="p5_w8" font-name="AGaramondPro" symbolic="yes" bold="no" italic="no" font-size="9.5" font-color="#231f1f" rotation="0" angle="0" x="405.777" y="32.1917" base="40.9032" width="9.5" height="12.0745">27</TOKEN></TEXT><TEXT width="345.807" height="13.981" x="69.4488" y="59.806" id="p5_t3"><TOKEN sid="p5_s1949" id="p5_w9" font-name="agaramondpro" symbolic="yes" bold="no" italic="no" font-size="11" font-color="#231f1f" rotation="0" angle="0" x="69.4488" y="59.806" base="69.893" width="5.016" height="13.981">•</TOKEN><TOKEN sid="p5_s1950" id="p5_w10" font-name="agaramondpro" symbolic="yes" bold="no" italic="no" font-size="11" font-color="#231f1f" rotation="0" angle="0" x="86.4548" y="59.806" base="69.893" width="45.243" height="13.981">Blakemore</TOKEN><TOKEN sid="p5_s1951" id="p5_w11" font-name="agaramondpro" symbolic="yes" bold="no" italic="no" font-size="11" font-color="#231f1f" rotation="0" angle="0" x="134.514" y="59.806" base="69.893" width="33.484" height="13.981">(2005a)</TOKEN><TOKEN sid="p5_s1952" id="p5_w12" font-name="agaramondpro" symbolic="yes" bold="no" italic="no" font-size="11" font-color="#231f1f" rotation="0" angle="0" x="170.814" y="59.806" base="69.893" width="24.453" height="13.981">noted</TOKEN><TOKEN sid="p5_s1953" id="p5_w13" font-name="agaramondpro" symbolic="yes" bold="no" italic="no" font-size="11" font-color="#231f1f" rotation="0" angle="0" x="198.083" y="59.806" base="69.893" width="16.863" height="13.981">that</TOKEN><TOKEN sid="p5_s1954" id="p5_w14" font-name="agaramondpro" symbolic="yes" bold="no" italic="no" font-size="11" font-color="#231f1f" rotation="0" angle="0" x="217.762" y="59.806" base="69.893" width="14.795" height="13.981">Lee</TOKEN><TOKEN sid="p5_s1955" id="p5_w15" font-name="agaramondpro" symbolic="yes" bold="no" italic="no" font-size="11" font-color="#231f1f" rotation="0" angle="0" x="235.373" y="59.806" base="69.893" width="29.04" height="13.981">(1962)</TOKEN><TOKEN sid="p5_s1956" id="p5_w16" font-name="agaramondpro" symbolic="yes" bold="no" italic="no" font-size="11" font-color="#231f1f" rotation="0" angle="0" x="267.229" y="59.806" base="69.893" width="23.056" height="13.981">made</TOKEN><TOKEN sid="p5_s1957" id="p5_w17" font-name="agaramondpro" symbolic="yes" bold="no" italic="yes" font-size="11" font-color="#231f1f" rotation="0" angle="0" x="293.101" y="59.806" base="69.893" width="47.729" height="13.805">Spenceriella</TOKEN><TOKEN sid="p5_s1958" id="p5_w18" font-name="agaramondpro" symbolic="yes" bold="no" italic="yes" font-size="11" font-color="#231f1f" rotation="0" angle="0" x="343.646" y="59.806" base="69.893" width="45.034" height="13.805">shakespeari</TOKEN><TOKEN sid="p5_s1959" id="p5_w19" font-name="agaramondpro" symbolic="yes" bold="no" italic="no" font-size="11" font-color="#231f1f" rotation="0" angle="0" x="391.496" y="59.806" base="69.893" width="23.76" height="13.981">(Ben-</TOKEN></TEXT><TEXT width="328.823" height="13.981" x="86.4548" y="73.006" id="p5_t4"><TOKEN sid="p5_s1960" id="p5_w20" font-name="agaramondpro" symbolic="yes" bold="no" italic="no" font-size="11" font-color="#231f1f" rotation="0" angle="0" x="86.4548" y="73.006" base="83.093" width="22.286" height="13.981">ham)</TOKEN><TOKEN sid="p5_s1961" id="p5_w21" font-name="agaramondpro" symbolic="yes" bold="no" italic="no" font-size="11" font-color="#231f1f" rotation="0" angle="0" x="111.788" y="73.006" base="83.093" width="26.015" height="13.981">junior</TOKEN><TOKEN sid="p5_s1962" id="p5_w22" font-name="agaramondpro" symbolic="yes" bold="no" italic="no" font-size="11" font-color="#231f1f" rotation="0" angle="0" x="140.85" y="73.006" base="83.093" width="38.742" height="13.981">synonym</TOKEN><TOKEN sid="p5_s1963" id="p5_w23" font-name="agaramondpro" symbolic="yes" bold="no" italic="no" font-size="11" font-color="#231f1f" rotation="0" angle="0" x="182.639" y="73.006" base="83.093" width="8.536" height="13.981">of</TOKEN><TOKEN sid="p5_s1964" id="p5_w24" font-name="agaramondpro" symbolic="yes" bold="no" italic="yes" font-size="11" font-color="#231f1f" rotation="0" angle="0" x="194.222" y="73.006" base="83.093" width="44.506" height="13.805">Megascolex</TOKEN><TOKEN sid="p5_s1965" id="p5_w25" font-name="agaramondpro" symbolic="yes" bold="no" italic="yes" font-size="11" font-color="#231f1f" rotation="0" angle="0" x="241.775" y="73.006" base="83.093" width="43.978" height="13.805">antarcticus</TOKEN><TOKEN sid="p5_s1966" id="p5_w26" font-name="agaramondpro" symbolic="yes" bold="no" italic="no" font-size="11" font-color="#231f1f" rotation="0" angle="0" x="288.8" y="73.006" base="83.093" width="25.641" height="13.981">Baird,</TOKEN><TOKEN sid="p5_s1967" id="p5_w27" font-name="agaramondpro" symbolic="yes" bold="no" italic="no" font-size="11" font-color="#231f1f" rotation="0" angle="0" x="317.488" y="73.006" base="83.093" width="20.02" height="13.981">itself</TOKEN><TOKEN sid="p5_s1968" id="p5_w28" font-name="agaramondpro" symbolic="yes" bold="no" italic="no" font-size="11" font-color="#231f1f" rotation="0" angle="0" x="340.555" y="73.006" base="83.093" width="45.496" height="13.981">transferred</TOKEN><TOKEN sid="p5_s1969" id="p5_w29" font-name="agaramondpro" symbolic="yes" bold="no" italic="no" font-size="11" font-color="#231f1f" rotation="0" angle="0" x="389.098" y="73.006" base="83.093" width="8.723" height="13.981">to</TOKEN><TOKEN sid="p5_s1970" id="p5_w30" font-name="agaramondpro" symbolic="yes" bold="no" italic="yes" font-size="11" font-color="#231f1f" rotation="0" angle="0" x="400.868" y="73.006" base="83.093" width="14.41" height="13.805">Ce-</TOKEN></TEXT><TEXT width="328.779" height="13.981" x="86.4548" y="86.206" id="p5_t5"><TOKEN sid="p5_s1971" id="p5_w31" font-name="agaramondpro" symbolic="yes" bold="no" italic="yes" font-size="11" font-color="#231f1f" rotation="0" angle="0" x="86.4548" y="86.206" base="96.293" width="27.423" height="13.805">leriella</TOKEN><TOKEN sid="p5_s1972" id="p5_w32" font-name="agaramondpro" symbolic="yes" bold="no" italic="no" font-size="11" font-color="#231f1f" rotation="0" angle="0" x="118.124" y="86.206" base="96.293" width="23.881" height="13.981">Gates</TOKEN><TOKEN sid="p5_s1973" id="p5_w33" font-name="agaramondpro" symbolic="yes" bold="no" italic="no" font-size="11" font-color="#231f1f" rotation="0" angle="0" x="146.251" y="86.206" base="96.293" width="37.752" height="13.981">although</TOKEN><TOKEN sid="p5_s1974" id="p5_w34" font-name="agaramondpro" symbolic="yes" bold="no" italic="no" font-size="11" font-color="#231f1f" rotation="0" angle="0" x="188.249" y="86.206" base="96.293" width="15.422" height="13.981">this</TOKEN><TOKEN sid="p5_s1975" id="p5_w35" font-name="agaramondpro" symbolic="yes" bold="no" italic="no" font-size="11" font-color="#231f1f" rotation="0" angle="0" x="207.917" y="86.206" base="96.293" width="31.603" height="13.981">appears</TOKEN><TOKEN sid="p5_s1976" id="p5_w36" font-name="agaramondpro" symbolic="yes" bold="no" italic="no" font-size="11" font-color="#231f1f" rotation="0" angle="0" x="243.766" y="86.206" base="96.293" width="8.723" height="13.981">to</TOKEN><TOKEN sid="p5_s1977" id="p5_w37" font-name="agaramondpro" symbolic="yes" bold="no" italic="no" font-size="11" font-color="#231f1f" rotation="0" angle="0" x="256.735" y="86.206" base="96.293" width="19.151" height="13.981">have</TOKEN><TOKEN sid="p5_s1978" id="p5_w38" font-name="agaramondpro" symbolic="yes" bold="no" italic="no" font-size="11" font-color="#231f1f" rotation="0" angle="0" x="280.132" y="86.206" base="96.293" width="19.987" height="13.981">been</TOKEN><TOKEN sid="p5_s1979" id="p5_w39" font-name="agaramondpro" symbolic="yes" bold="no" italic="no" font-size="11" font-color="#231f1f" rotation="0" angle="0" x="304.365" y="86.206" base="96.293" width="46.53" height="13.981">overlooked</TOKEN><TOKEN sid="p5_s1980" id="p5_w40" font-name="agaramondpro" symbolic="yes" bold="no" italic="no" font-size="11" font-color="#231f1f" rotation="0" angle="0" x="355.141" y="86.206" base="96.293" width="8.998" height="13.981">or</TOKEN><TOKEN sid="p5_s1981" id="p5_w41" font-name="agaramondpro" symbolic="yes" bold="no" italic="no" font-size="11" font-color="#231f1f" rotation="0" angle="0" x="368.385" y="86.206" base="96.293" width="32.351" height="13.981">ignored</TOKEN><TOKEN sid="p5_s1982" id="p5_w42" font-name="agaramondpro" symbolic="yes" bold="no" italic="no" font-size="11" font-color="#231f1f" rotation="0" angle="0" x="404.982" y="86.206" base="96.293" width="10.252" height="13.981">by</TOKEN></TEXT><TEXT width="328.834" height="13.981" x="86.4548" y="99.406" id="p5_t6"><TOKEN sid="p5_s1983" id="p5_w43" font-name="agaramondpro" symbolic="yes" bold="no" italic="no" font-size="11" font-color="#231f1f" rotation="0" angle="0" x="86.4548" y="99.406" base="109.493" width="33.748" height="13.981">Buckley</TOKEN><TOKEN sid="p5_s1984" id="p5_w44" font-name="agaramondpro" symbolic="yes" bold="no" italic="no" font-size="11" font-color="#231f1f" rotation="0" angle="0" x="122.612" y="99.406" base="109.493" width="7.733" height="13.981">et</TOKEN><TOKEN sid="p5_s1985" id="p5_w45" font-name="agaramondpro" symbolic="yes" bold="no" italic="no" font-size="11" font-color="#231f1f" rotation="0" angle="0" x="132.743" y="99.406" base="109.493" width="9.911" height="13.981">al.</TOKEN><TOKEN sid="p5_s1986" id="p5_w46" font-name="agaramondpro" symbolic="yes" bold="no" italic="no" font-size="11" font-color="#231f1f" rotation="0" angle="0" x="145.063" y="99.406" base="109.493" width="28.27" height="13.981">(2011:</TOKEN><TOKEN sid="p5_s1987" id="p5_w47" font-name="agaramondpro" symbolic="yes" bold="no" italic="no" font-size="11" font-color="#231f1f" rotation="0" angle="0" x="175.742" y="99.406" base="109.493" width="41.184" height="13.981">Appendix</TOKEN><TOKEN sid="p5_s1988" id="p5_w48" font-name="agaramondpro" symbolic="yes" bold="no" italic="no" font-size="11" font-color="#231f1f" rotation="0" angle="0" x="219.324" y="99.406" base="109.493" width="10.373" height="13.981">A)</TOKEN><TOKEN sid="p5_s1989" id="p5_w49" font-name="agaramondpro" symbolic="yes" bold="no" italic="no" font-size="11" font-color="#231f1f" rotation="0" angle="0" x="232.106" y="99.406" base="109.493" width="18.271" height="13.981">who</TOKEN><TOKEN sid="p5_s1990" id="p5_w50" font-name="agaramondpro" symbolic="yes" bold="no" italic="no" font-size="11" font-color="#231f1f" rotation="0" angle="0" x="252.786" y="99.406" base="109.493" width="12.485" height="13.981">yet</TOKEN><TOKEN sid="p5_s1991" id="p5_w51" font-name="agaramondpro" symbolic="yes" bold="no" italic="no" font-size="11" font-color="#231f1f" rotation="0" angle="0" x="267.68" y="99.406" base="109.493" width="23.045" height="13.981">claim</TOKEN><TOKEN sid="p5_s1992" id="p5_w52" font-name="agaramondpro" symbolic="yes" bold="no" italic="no" font-size="11" font-color="#231f1f" rotation="0" angle="0" x="293.123" y="99.406" base="109.493" width="8.723" height="13.981">to</TOKEN><TOKEN sid="p5_s1993" id="p5_w53" font-name="agaramondpro" symbolic="yes" bold="no" italic="no" font-size="11" font-color="#231f1f" rotation="0" angle="0" x="304.255" y="99.406" base="109.493" width="19.151" height="13.981">have</TOKEN><TOKEN sid="p5_s1994" id="p5_w54" font-name="agaramondpro" symbolic="yes" bold="no" italic="no" font-size="11" font-color="#231f1f" rotation="0" angle="0" x="325.804" y="99.406" base="109.493" width="34.903" height="13.981">sampled</TOKEN><TOKEN sid="p5_s1995" id="p5_w55" font-name="agaramondpro" symbolic="yes" bold="no" italic="no" font-size="11" font-color="#231f1f" rotation="0" angle="0" x="363.116" y="99.406" base="109.493" width="52.173" height="13.981">“Spenceriella</TOKEN></TEXT><TEXT width="328.845" height="13.981" x="86.4548" y="112.606" id="p5_t7"><TOKEN sid="p5_s1996" id="p5_w56" font-name="agaramondpro" symbolic="yes" bold="no" italic="yes" font-size="11" font-color="#231f1f" rotation="0" angle="0" x="86.4548" y="112.606" base="122.693" width="49.478" height="13.805">shakespeari”</TOKEN><TOKEN sid="p5_s1997" id="p5_w57" font-name="agaramondpro" symbolic="yes" bold="no" italic="no" font-size="11" font-color="#231f1f" rotation="0" angle="0" x="138.342" y="112.606" base="122.693" width="35.244" height="13.981">(WM93</TOKEN><TOKEN sid="p5_s1998" id="p5_w58" font-name="agaramondpro" symbolic="yes" bold="no" italic="no" font-size="11" font-color="#231f1f" rotation="0" angle="0" x="175.995" y="112.606" base="122.693" width="20.779" height="13.981">from</TOKEN><TOKEN sid="p5_s1999" id="p5_w59" font-name="agaramondpro" symbolic="yes" bold="no" italic="no" font-size="11" font-color="#231f1f" rotation="0" angle="0" x="199.018" y="112.606" base="122.693" width="37.873" height="13.981">Waharau</TOKEN><TOKEN sid="p5_s2000" id="p5_w60" font-name="agaramondpro" symbolic="yes" bold="no" italic="no" font-size="11" font-color="#231f1f" rotation="0" angle="0" x="239.3" y="112.606" base="122.693" width="14.091" height="13.981">Pk,</TOKEN><TOKEN sid="p5_s2001" id="p5_w61" font-name="agaramondpro" symbolic="yes" bold="no" italic="no" font-size="11" font-color="#231f1f" rotation="0" angle="0" x="255.8" y="112.606" base="122.693" width="30.019" height="13.981">Hunua</TOKEN><TOKEN sid="p5_s2002" id="p5_w62" font-name="agaramondpro" symbolic="yes" bold="no" italic="no" font-size="11" font-color="#231f1f" rotation="0" angle="0" x="288.228" y="112.606" base="122.693" width="30.096" height="13.981">Range)</TOKEN><TOKEN sid="p5_s2003" id="p5_w63" font-name="agaramondpro" symbolic="yes" bold="no" italic="no" font-size="11" font-color="#231f1f" rotation="0" angle="0" x="320.733" y="112.606" base="122.693" width="14.509" height="13.981">but</TOKEN><TOKEN sid="p5_s2004" id="p5_w64" font-name="agaramondpro" symbolic="yes" bold="no" italic="no" font-size="11" font-color="#231f1f" rotation="0" angle="0" x="337.651" y="112.606" base="122.693" width="28.05" height="13.981">appear</TOKEN><TOKEN sid="p5_s2005" id="p5_w65" font-name="agaramondpro" symbolic="yes" bold="no" italic="no" font-size="11" font-color="#231f1f" rotation="0" angle="0" x="368.11" y="112.606" base="122.693" width="14.498" height="13.981">not</TOKEN><TOKEN sid="p5_s2006" id="p5_w66" font-name="agaramondpro" symbolic="yes" bold="no" italic="no" font-size="11" font-color="#231f1f" rotation="0" angle="0" x="385.017" y="112.606" base="122.693" width="8.723" height="13.981">to</TOKEN><TOKEN sid="p5_s2007" id="p5_w67" font-name="agaramondpro" symbolic="yes" bold="no" italic="no" font-size="11" font-color="#231f1f" rotation="0" angle="0" x="396.149" y="112.606" base="122.693" width="19.151" height="13.981">have</TOKEN></TEXT><TEXT width="85.547" height="13.981" x="86.4548" y="125.806" id="p5_t8"><TOKEN sid="p5_s2008" id="p5_w68" font-name="agaramondpro" symbolic="yes" bold="no" italic="no" font-size="11" font-color="#231f1f" rotation="0" angle="0" x="86.4548" y="125.806" base="135.893" width="43.494" height="13.981">sequenced</TOKEN><TOKEN sid="p5_s2009" id="p5_w69" font-name="agaramondpro" symbolic="yes" bold="no" italic="no" font-size="11" font-color="#231f1f" rotation="0" angle="0" x="132.699" y="125.806" base="135.893" width="9.757" height="13.981">its</TOKEN><TOKEN sid="p5_s2010" id="p5_w70" font-name="agaramondpro" symbolic="yes" bold="no" italic="no" font-size="11" font-color="#231f1f" rotation="0" angle="0" x="145.206" y="125.806" base="135.893" width="26.796" height="13.981">DNA.</TOKEN></TEXT><TEXT width="345.785" height="13.981" x="69.4488" y="139.006" id="p5_t9"><TOKEN sid="p5_s2011" id="p5_w71" font-name="agaramondpro" symbolic="yes" bold="no" italic="no" font-size="11" font-color="#231f1f" rotation="0" angle="0" x="69.4488" y="139.006" base="149.093" width="5.016" height="13.981">•</TOKEN><TOKEN sid="p5_s2012" id="p5_w72" font-name="agaramondpro" symbolic="yes" bold="no" italic="no" font-size="11" font-color="#231f1f" rotation="0" angle="0" x="86.4548" y="139.006" base="149.093" width="12.287" height="13.981">All</TOKEN><TOKEN sid="p5_s2013" id="p5_w73" font-name="agaramondpro" symbolic="yes" bold="no" italic="no" font-size="11" font-color="#231f1f" rotation="0" angle="0" x="102.999" y="139.006" base="149.093" width="56.793" height="13.981">“Michaelesen</TOKEN><TOKEN sid="p5_s2014" id="p5_w74" font-name="agaramondpro" symbolic="yes" bold="no" italic="no" font-size="11" font-color="#231f1f" rotation="0" angle="0" x="164.049" y="139.006" base="149.093" width="33.484" height="13.981">(1923)”</TOKEN><TOKEN sid="p5_s2015" id="p5_w75" font-name="agaramondpro" symbolic="yes" bold="no" italic="no" font-size="11" font-color="#231f1f" rotation="0" angle="0" x="201.79" y="139.006" base="149.093" width="28.622" height="13.981">species</TOKEN><TOKEN sid="p5_s2016" id="p5_w76" href="http://ia700402.us.archive.org/4/items/videnskabeligeme74dans/videnskabeligeme74dans_bw.pdf" font-name="agaramondpro" symbolic="yes" bold="no" italic="no" font-size="11" font-color="#231f1f" rotation="0" angle="0" x="234.669" y="139.006" base="149.093" width="28.512" height="13.981">should</TOKEN><TOKEN sid="p5_s2017" id="p5_w77" href="http://ia700402.us.archive.org/4/items/videnskabeligeme74dans/videnskabeligeme74dans_bw.pdf" font-name="agaramondpro" symbolic="yes" bold="no" italic="no" font-size="11" font-color="#231f1f" rotation="0" angle="0" x="267.449" y="139.006" base="149.093" width="9.856" height="13.981">be</TOKEN><TOKEN sid="p5_s2018" id="p5_w78" href="http://ia700402.us.archive.org/4/items/videnskabeligeme74dans/videnskabeligeme74dans_bw.pdf" font-name="agaramondpro" symbolic="yes" bold="no" italic="no" font-size="11" font-color="#231f1f" rotation="0" angle="0" x="281.562" y="139.006" base="149.093" width="35.145" height="13.981">changed</TOKEN><TOKEN sid="p5_s2019" id="p5_w79" href="http://ia700402.us.archive.org/4/items/videnskabeligeme74dans/videnskabeligeme74dans_bw.pdf" font-name="agaramondpro" symbolic="yes" bold="no" italic="no" font-size="11" font-color="#231f1f" rotation="0" angle="0" x="320.964" y="139.006" base="149.093" width="8.723" height="13.981">to</TOKEN><TOKEN sid="p5_s2020" id="p5_w80" href="http://ia700402.us.archive.org/4/items/videnskabeligeme74dans/videnskabeligeme74dans_bw.pdf" font-name="agaramondpro" symbolic="yes" bold="no" italic="no" font-size="11" font-color="#231f1f" rotation="0" angle="0" x="333.944" y="139.006" base="149.093" width="47.993" height="13.981">Michaelsen</TOKEN><TOKEN sid="p5_s2021" id="p5_w81" href="http://ia700402.us.archive.org/4/items/videnskabeligeme74dans/videnskabeligeme74dans_bw.pdf" font-name="agaramondpro" symbolic="yes" bold="no" italic="no" font-size="11" font-color="#231f1f" rotation="0" angle="0" x="386.194" y="139.006" base="149.093" width="29.04" height="13.981">(1924)</TOKEN></TEXT><TEXT width="328.801" height="13.981" x="86.4548" y="152.206" id="p5_t10"><TOKEN sid="p5_s2022" id="p5_w82" href="http://ia700402.us.archive.org/4/items/videnskabeligeme74dans/videnskabeligeme74dans_bw.pdf" font-name="agaramondpro" symbolic="yes" bold="no" italic="no" font-size="11" font-color="#231f1f" rotation="0" angle="0" x="86.4548" y="152.206" base="162.293" width="41.195" height="13.981">according</TOKEN><TOKEN sid="p5_s2023" id="p5_w83" href="http://ia700402.us.archive.org/4/items/videnskabeligeme74dans/videnskabeligeme74dans_bw.pdf" font-name="agaramondpro" symbolic="yes" bold="no" italic="no" font-size="11" font-color="#231f1f" rotation="0" angle="0" x="130.961" y="152.206" base="162.293" width="8.723" height="13.981">to</TOKEN><TOKEN sid="p5_s2024" id="p5_w84" href="http://ia700402.us.archive.org/4/items/videnskabeligeme74dans/videnskabeligeme74dans_bw.pdf" font-name="agaramondpro" symbolic="yes" bold="no" italic="no" font-size="11" font-color="#231f1f" rotation="0" angle="0" x="142.995" y="152.206" base="162.293" width="13.398" height="13.981">the</TOKEN><TOKEN sid="p5_s2025" id="p5_w85" href="http://ia700402.us.archive.org/4/items/videnskabeligeme74dans/videnskabeligeme74dans_bw.pdf" font-name="agaramondpro" symbolic="yes" bold="no" italic="no" font-size="11" font-color="#231f1f" rotation="0" angle="0" x="159.704" y="152.206" base="162.293" width="31.394" height="13.981">volume</TOKEN><TOKEN sid="p5_s2026" id="p5_w86" href="http://ia700402.us.archive.org/4/items/videnskabeligeme74dans/videnskabeligeme74dans_bw.pdf" font-name="agaramondpro" symbolic="yes" bold="no" italic="no" font-size="11" font-color="#231f1f" rotation="0" angle="0" x="194.409" y="152.206" base="162.293" width="29.865" height="13.981">preface</TOKEN><TOKEN sid="p5_s2027" id="p5_w87" href="http://ia700402.us.archive.org/4/items/videnskabeligeme74dans/videnskabeligeme74dans_bw.pdf" font-name="agaramondpro" symbolic="yes" bold="no" italic="no" font-size="11" font-color="#231f1f" rotation="0" angle="0" x="227.585" y="152.206" base="162.293" width="15.785" height="13.981">(see</TOKEN><TOKEN sid="p5_s2028" id="p5_w88" href="http://ia700402.us.archive.org/4/items/videnskabeligeme74dans/videnskabeligeme74dans_bw.pdf" font-name="agaramondpro" symbolic="yes" bold="no" italic="no" font-size="11" font-color="#231f1f" rotation="0" angle="0" x="246.681" y="152.206" base="162.293" width="168.575" height="13.981">http://ia700402.us.archive.org/4/items/</TOKEN></TEXT><TEXT width="328.812" height="13.981" x="86.4548" y="165.406" id="p5_t11"><TOKEN sid="p5_s2029" id="p5_w89" href="http://ia700402.us.archive.org/4/items/videnskabeligeme74dans/videnskabeligeme74dans_bw.pdf" font-name="agaramondpro" symbolic="yes" bold="no" italic="no" font-size="11" font-color="#231f1f" rotation="0" angle="0" x="86.4548" y="165.406" base="175.493" width="247.39" height="13.981">videnskabeligeme74dans/videnskabeligeme74dans_bw.pdf</TOKEN><TOKEN sid="p5_s2030" id="p5_w90" href="http://ia700402.us.archive.org/4/items/videnskabeligeme74dans/videnskabeligeme74dans_bw.pdf" font-name="agaramondpro" symbolic="yes" bold="no" italic="no" font-size="11" font-color="#231f1f" rotation="0" angle="0" x="345.197" y="165.406" base="175.493" width="34.661" height="13.981">accessed</TOKEN><TOKEN sid="p5_s2031" id="p5_w91" href="http://ia700402.us.archive.org/4/items/videnskabeligeme74dans/videnskabeligeme74dans_bw.pdf" font-name="agaramondpro" symbolic="yes" bold="no" italic="no" font-size="11" font-color="#231f1f" rotation="0" angle="0" x="391.21" y="165.406" base="175.493" width="24.057" height="13.981">Sept.,</TOKEN></TEXT><TEXT width="252.813" height="13.981" id="p5_t12" x="86.4548" y="178.606"><TOKEN sid="p5_s2032" id="p5_w92" href="http://ia700402.us.archive.org/4/items/videnskabeligeme74dans/videnskabeligeme74dans_bw.pdf" font-name="agaramondpro" symbolic="yes" bold="no" italic="no" font-size="11" font-color="#231f1f" rotation="0" angle="0" x="86.4548" y="178.606" base="188.693" width="25.52" height="13.981">2011)</TOKEN><TOKEN sid="p5_s2033" id="p5_w93" href="http://ia700402.us.archive.org/4/items/videnskabeligeme74dans/videnskabeligeme74dans_bw.pdf" font-name="agaramondpro" symbolic="yes" bold="no" italic="no" font-size="11" font-color="#231f1f" rotation="0" angle="0" x="114.725" y="178.606" base="188.693" width="15.818" height="13.981">and</TOKEN><TOKEN sid="p5_s2034" id="p5_w94" href="http://ia700402.us.archive.org/4/items/videnskabeligeme74dans/videnskabeligeme74dans_bw.pdf" font-name="agaramondpro" symbolic="yes" bold="no" italic="no" font-size="11" font-color="#231f1f" rotation="0" angle="0" x="133.293" y="178.606" base="188.693" width="15.477" height="13.981">one</TOKEN><TOKEN sid="p5_s2035" id="p5_w95" href="http://ia700402.us.archive.org/4/items/videnskabeligeme74dans/videnskabeligeme74dans_bw.pdf" font-name="agaramondpro" symbolic="yes" bold="no" italic="no" font-size="11" font-color="#231f1f" rotation="0" angle="0" x="151.52" y="178.606" base="188.693" width="8.536" height="13.981">of</TOKEN><TOKEN sid="p5_s2036" id="p5_w96" href="http://ia700402.us.archive.org/4/items/videnskabeligeme74dans/videnskabeligeme74dans_bw.pdf" font-name="agaramondpro" symbolic="yes" bold="no" italic="no" font-size="11" font-color="#231f1f" rotation="0" angle="0" x="162.806" y="178.606" base="188.693" width="24.057" height="13.981">these,</TOKEN><TOKEN sid="p5_s2037" id="p5_w97" href="http://ia700402.us.archive.org/4/items/videnskabeligeme74dans/videnskabeligeme74dans_bw.pdf" font-name="agaramondpro" symbolic="yes" bold="no" italic="yes" font-size="11" font-color="#231f1f" rotation="0" angle="0" x="189.613" y="178.606" base="188.693" width="10.879" height="13.805">N.</TOKEN><TOKEN sid="p5_s2038" id="p5_w98" href="http://ia700402.us.archive.org/4/items/videnskabeligeme74dans/videnskabeligeme74dans_bw.pdf" font-name="agaramondpro" symbolic="yes" bold="no" italic="yes" font-size="11" font-color="#231f1f" rotation="0" angle="0" x="203.242" y="178.606" base="188.693" width="46.772" height="13.805">mortenseni,</TOKEN><TOKEN sid="p5_s2039" id="p5_w99" href="http://ia700402.us.archive.org/4/items/videnskabeligeme74dans/videnskabeligeme74dans_bw.pdf" font-name="agaramondpro" symbolic="yes" bold="no" italic="no" font-size="11" font-color="#231f1f" rotation="0" angle="0" x="252.764" y="178.606" base="188.693" width="6.38" height="13.981">is</TOKEN><TOKEN sid="p5_s2040" id="p5_w100" href="http://ia700402.us.archive.org/4/items/videnskabeligeme74dans/videnskabeligeme74dans_bw.pdf" font-name="agaramondpro" symbolic="yes" bold="no" italic="no" font-size="11" font-color="#231f1f" rotation="0" angle="0" x="261.894" y="178.606" base="188.693" width="45.353" height="13.981">considered</TOKEN><TOKEN sid="p5_s2041" id="p5_w101" href="http://ia700402.us.archive.org/4/items/videnskabeligeme74dans/videnskabeligeme74dans_bw.pdf" font-name="agaramondpro" symbolic="yes" bold="no" italic="no" font-size="11" font-color="#231f1f" rotation="0" angle="0" x="309.997" y="178.606" base="188.693" width="29.271" height="13.981">herein.</TOKEN></TEXT><TEXT width="44.33" height="12.749" id="p5_t13" x="52.4428" y="223.706"><TOKEN sid="p5_s2042" id="p5_w102" font-name="GillSans" serif="yes" bold="yes" italic="no" font-size="11" font-color="#231f1f" rotation="0" angle="0" x="52.4428" y="223.706" base="233.925" width="44.33" height="12.749">Methods</TOKEN></TEXT><TEXT width="362.791" height="13.981" x="52.4428" y="244.606" id="p5_t14"><TOKEN sid="p5_s2043" id="p5_w103" font-name="agaramondpro" symbolic="yes" bold="no" italic="no" font-size="11" font-color="#231f1f" rotation="0" angle="0" x="52.4428" y="244.606" base="254.693" width="44.616" height="13.981">Specimens</TOKEN><TOKEN sid="p5_s2044" id="p5_w104" font-name="agaramondpro" symbolic="yes" bold="no" italic="no" font-size="11" font-color="#231f1f" rotation="0" angle="0" x="99.9738" y="244.606" base="254.693" width="19.448" height="13.981">were</TOKEN><TOKEN sid="p5_s2045" id="p5_w105" font-name="agaramondpro" symbolic="yes" bold="no" italic="no" font-size="11" font-color="#231f1f" rotation="0" angle="0" x="122.337" y="244.606" base="254.693" width="39.358" height="13.981">sketched,</TOKEN><TOKEN sid="p5_s2046" id="p5_w106" font-name="agaramondpro" symbolic="yes" bold="no" italic="no" font-size="11" font-color="#231f1f" rotation="0" angle="0" x="164.61" y="244.606" base="254.693" width="37.62" height="13.981">dissected</TOKEN><TOKEN sid="p5_s2047" id="p5_w107" font-name="agaramondpro" symbolic="yes" bold="no" italic="no" font-size="11" font-color="#231f1f" rotation="0" angle="0" x="205.145" y="244.606" base="254.693" width="15.818" height="13.981">and</TOKEN><TOKEN sid="p5_s2048" id="p5_w108" font-name="agaramondpro" symbolic="yes" bold="no" italic="no" font-size="11" font-color="#231f1f" rotation="0" angle="0" x="223.878" y="244.606" base="254.693" width="39.842" height="13.981">described</TOKEN><TOKEN sid="p5_s2049" id="p5_w109" font-name="agaramondpro" symbolic="yes" bold="no" italic="no" font-size="11" font-color="#231f1f" rotation="0" angle="0" x="266.635" y="244.606" base="254.693" width="25.014" height="13.981">under</TOKEN><TOKEN sid="p5_s2050" id="p5_w110" font-name="agaramondpro" symbolic="yes" bold="no" italic="no" font-size="11" font-color="#231f1f" rotation="0" angle="0" x="294.564" y="244.606" base="254.693" width="15.191" height="13.981">low</TOKEN><TOKEN sid="p5_s2051" id="p5_w111" font-name="agaramondpro" symbolic="yes" bold="no" italic="no" font-size="11" font-color="#231f1f" rotation="0" angle="0" x="312.67" y="244.606" base="254.693" width="25.993" height="13.981">power</TOKEN><TOKEN sid="p5_s2052" id="p5_w112" font-name="agaramondpro" symbolic="yes" bold="no" italic="no" font-size="11" font-color="#231f1f" rotation="0" angle="0" x="341.578" y="244.606" base="254.693" width="48.048" height="13.981">microscope</TOKEN><TOKEN sid="p5_s2053" id="p5_w113" font-name="agaramondpro" symbolic="yes" bold="no" italic="no" font-size="11" font-color="#231f1f" rotation="0" angle="0" x="392.541" y="244.606" base="254.693" width="22.693" height="13.981">using</TOKEN></TEXT><TEXT width="362.824" height="13.981" x="52.4428" y="257.806" id="p5_t15"><TOKEN sid="p5_s2054" id="p5_w114" font-name="agaramondpro" symbolic="yes" bold="no" italic="no" font-size="11" font-color="#231f1f" rotation="0" angle="0" x="52.4428" y="257.806" base="267.893" width="13.398" height="13.981">the</TOKEN><TOKEN sid="p5_s2055" id="p5_w115" font-name="agaramondpro" symbolic="yes" bold="no" italic="no" font-size="11" font-color="#231f1f" rotation="0" angle="0" x="68.6568" y="257.806" base="267.893" width="45.408" height="13.981">techniques</TOKEN><TOKEN sid="p5_s2056" id="p5_w116" font-name="agaramondpro" symbolic="yes" bold="no" italic="no" font-size="11" font-color="#231f1f" rotation="0" angle="0" x="116.881" y="257.806" base="267.893" width="15.818" height="13.981">and</TOKEN><TOKEN sid="p5_s2057" id="p5_w117" font-name="agaramondpro" symbolic="yes" bold="no" italic="no" font-size="11" font-color="#231f1f" rotation="0" angle="0" x="135.515" y="257.806" base="267.893" width="51.216" height="13.981">conventions</TOKEN><TOKEN sid="p5_s2058" id="p5_w118" font-name="agaramondpro" symbolic="yes" bold="no" italic="no" font-size="11" font-color="#231f1f" rotation="0" angle="0" x="189.547" y="257.806" base="267.893" width="24.453" height="13.981">noted</TOKEN><TOKEN sid="p5_s2059" id="p5_w119" font-name="agaramondpro" symbolic="yes" bold="no" italic="no" font-size="11" font-color="#231f1f" rotation="0" angle="0" x="216.816" y="257.806" base="267.893" width="8.602" height="13.981">in</TOKEN><TOKEN sid="p5_s2060" id="p5_w120" font-name="agaramondpro" symbolic="yes" bold="no" italic="no" font-size="11" font-color="#231f1f" rotation="0" angle="0" x="228.234" y="257.806" base="267.893" width="45.243" height="13.981">Blakemore</TOKEN><TOKEN sid="p5_s2061" id="p5_w121" font-name="agaramondpro" symbolic="yes" bold="no" italic="no" font-size="11" font-color="#231f1f" rotation="0" angle="0" x="276.293" y="257.806" base="267.893" width="28.27" height="13.981">(2000,</TOKEN><TOKEN sid="p5_s2062" id="p5_w122" font-name="agaramondpro" symbolic="yes" bold="no" italic="no" font-size="11" font-color="#231f1f" rotation="0" angle="0" x="307.379" y="257.806" base="267.893" width="24.75" height="13.981">2002,</TOKEN><TOKEN sid="p5_s2063" id="p5_w123" font-name="agaramondpro" symbolic="yes" bold="no" italic="no" font-size="11" font-color="#231f1f" rotation="0" angle="0" x="334.945" y="257.806" base="267.893" width="28.27" height="13.981">2008).</TOKEN><TOKEN sid="p5_s2064" id="p5_w124" font-name="agaramondpro" symbolic="yes" bold="no" italic="no" font-size="11" font-color="#231f1f" rotation="0" angle="0" x="365.536" y="257.806" base="267.893" width="26.741" height="13.981">Tissue</TOKEN><TOKEN sid="p5_s2065" id="p5_w125" font-name="agaramondpro" symbolic="yes" bold="no" italic="no" font-size="11" font-color="#231f1f" rotation="0" angle="0" x="395.093" y="257.806" base="267.893" width="20.174" height="13.981">sam-</TOKEN></TEXT><TEXT width="362.824" height="13.981" x="52.4428" y="271.006" id="p5_t16"><TOKEN sid="p5_s2066" id="p5_w126" font-name="agaramondpro" symbolic="yes" bold="no" italic="no" font-size="11" font-color="#231f1f" rotation="0" angle="0" x="52.4428" y="271.006" base="281.093" width="16.203" height="13.981">ples</TOKEN><TOKEN sid="p5_s2067" id="p5_w127" font-name="agaramondpro" symbolic="yes" bold="no" italic="no" font-size="11" font-color="#231f1f" rotation="0" angle="0" x="71.9678" y="271.006" base="281.093" width="19.448" height="13.981">were</TOKEN><TOKEN sid="p5_s2068" id="p5_w128" font-name="agaramondpro" symbolic="yes" bold="no" italic="no" font-size="11" font-color="#231f1f" rotation="0" angle="0" x="94.7378" y="271.006" base="281.093" width="23.254" height="13.981">taken</TOKEN><TOKEN sid="p5_s2069" id="p5_w129" font-name="agaramondpro" symbolic="yes" bold="no" italic="no" font-size="11" font-color="#231f1f" rotation="0" angle="0" x="121.314" y="271.006" base="281.093" width="20.779" height="13.981">from</TOKEN><TOKEN sid="p5_s2070" id="p5_w130" font-name="agaramondpro" symbolic="yes" bold="no" italic="no" font-size="11" font-color="#231f1f" rotation="0" angle="0" x="145.415" y="271.006" base="281.093" width="17.457" height="13.981">new</TOKEN><TOKEN sid="p5_s2071" id="p5_w131" font-name="agaramondpro" symbolic="yes" bold="no" italic="no" font-size="11" font-color="#231f1f" rotation="0" angle="0" x="166.194" y="271.006" base="281.093" width="50.27" height="13.981">type-species</TOKEN><TOKEN sid="p5_s2072" id="p5_w132" font-name="agaramondpro" symbolic="yes" bold="no" italic="no" font-size="11" font-color="#231f1f" rotation="0" angle="0" x="219.786" y="271.006" base="281.093" width="8.723" height="13.981">to</TOKEN><TOKEN sid="p5_s2073" id="p5_w133" font-name="agaramondpro" symbolic="yes" bold="no" italic="no" font-size="11" font-color="#231f1f" rotation="0" angle="0" x="231.831" y="271.006" base="281.093" width="33.165" height="13.981">attempt</TOKEN><TOKEN sid="p5_s2074" id="p5_w134" font-name="agaramondpro" symbolic="yes" bold="no" italic="no" font-size="11" font-color="#231f1f" rotation="0" angle="0" x="268.318" y="271.006" base="281.093" width="47.762" height="13.981">DNA/COI</TOKEN><TOKEN sid="p5_s2075" id="p5_w135" font-name="agaramondpro" symbolic="yes" bold="no" italic="no" font-size="11" font-color="#231f1f" rotation="0" angle="0" x="319.402" y="271.006" base="281.093" width="33.231" height="13.981">barcode</TOKEN><TOKEN sid="p5_s2076" id="p5_w136" font-name="agaramondpro" symbolic="yes" bold="no" italic="no" font-size="11" font-color="#231f1f" rotation="0" angle="0" x="355.955" y="271.006" base="281.093" width="32.131" height="13.981">analysis</TOKEN><TOKEN sid="p5_s2077" id="p5_w137" font-name="agaramondpro" symbolic="yes" bold="no" italic="no" font-size="11" font-color="#231f1f" rotation="0" angle="0" x="391.408" y="271.006" base="281.093" width="5.5" height="13.981">–</TOKEN><TOKEN sid="p5_s2078" id="p5_w138" font-name="agaramondpro" symbolic="yes" bold="no" italic="no" font-size="11" font-color="#231f1f" rotation="0" angle="0" x="400.23" y="271.006" base="281.093" width="15.037" height="13.981">any</TOKEN></TEXT><TEXT width="362.78" height="13.981" x="52.4428" y="284.206" id="p5_t17"><TOKEN sid="p5_s2079" id="p5_w139" font-name="agaramondpro" symbolic="yes" bold="no" italic="no" font-size="11" font-color="#231f1f" rotation="0" angle="0" x="52.4428" y="284.206" base="294.293" width="26.73" height="13.981">results</TOKEN><TOKEN sid="p5_s2080" id="p5_w140" font-name="agaramondpro" symbolic="yes" bold="no" italic="no" font-size="11" font-color="#231f1f" rotation="0" angle="0" x="81.6918" y="284.206" base="294.293" width="12.342" height="13.981">are</TOKEN><TOKEN sid="p5_s2081" id="p5_w141" font-name="agaramondpro" symbolic="yes" bold="no" italic="no" font-size="11" font-color="#231f1f" rotation="0" angle="0" x="96.5528" y="284.206" base="294.293" width="8.723" height="13.981">to</TOKEN><TOKEN sid="p5_s2082" id="p5_w142" font-name="agaramondpro" symbolic="yes" bold="no" italic="no" font-size="11" font-color="#231f1f" rotation="0" angle="0" x="107.795" y="284.206" base="294.293" width="9.856" height="13.981">be</TOKEN><TOKEN sid="p5_s2083" id="p5_w143" font-name="agaramondpro" symbolic="yes" bold="no" italic="no" font-size="11" font-color="#231f1f" rotation="0" angle="0" x="120.17" y="284.206" base="294.293" width="27.808" height="13.981">posted</TOKEN><TOKEN sid="p5_s2084" id="p5_w144" font-name="agaramondpro" symbolic="yes" bold="no" italic="no" font-size="11" font-color="#231f1f" rotation="0" angle="0" x="150.497" y="284.206" base="294.293" width="8.602" height="13.981">in</TOKEN><TOKEN sid="p5_s2085" id="p5_w145" font-name="agaramondpro" symbolic="yes" bold="no" italic="no" font-size="11" font-color="#231f1f" rotation="0" angle="0" x="161.618" y="284.206" base="294.293" width="43.076" height="13.981">GenBank.</TOKEN><TOKEN sid="p5_s2086" id="p5_w146" font-name="agaramondpro" symbolic="yes" bold="no" italic="no" font-size="11" font-color="#231f1f" rotation="0" angle="0" x="207.213" y="284.206" base="294.293" width="56.661" height="13.981">Classification</TOKEN><TOKEN sid="p5_s2087" id="p5_w147" font-name="agaramondpro" symbolic="yes" bold="no" italic="no" font-size="11" font-color="#231f1f" rotation="0" angle="0" x="266.393" y="284.206" base="294.293" width="29.997" height="13.981">follows</TOKEN><TOKEN sid="p5_s2088" id="p5_w148" font-name="agaramondpro" symbolic="yes" bold="no" italic="no" font-size="11" font-color="#231f1f" rotation="0" angle="0" x="298.909" y="284.206" base="294.293" width="45.243" height="13.981">Blakemore</TOKEN><TOKEN sid="p5_s2089" id="p5_w149" font-name="agaramondpro" symbolic="yes" bold="no" italic="no" font-size="11" font-color="#231f1f" rotation="0" angle="0" x="346.671" y="284.206" base="294.293" width="29.04" height="13.981">(2000)</TOKEN><TOKEN sid="p5_s2090" id="p5_w150" font-name="agaramondpro" symbolic="yes" bold="no" italic="no" font-size="11" font-color="#231f1f" rotation="0" angle="0" x="378.23" y="284.206" base="294.293" width="7.821" height="13.981">at</TOKEN><TOKEN sid="p5_s2091" id="p5_w151" font-name="agaramondpro" symbolic="yes" bold="no" italic="no" font-size="11" font-color="#231f1f" rotation="0" angle="0" x="388.57" y="284.206" base="294.293" width="26.653" height="13.981">family</TOKEN></TEXT><TEXT width="362.879" height="13.981" x="52.4428" y="297.406" id="p5_t18"><TOKEN sid="p5_s2092" id="p5_w152" font-name="agaramondpro" symbolic="yes" bold="no" italic="no" font-size="11" font-color="#231f1f" rotation="0" angle="0" x="52.4428" y="297.406" base="307.493" width="18.832" height="13.981">level</TOKEN><TOKEN sid="p5_s2093" id="p5_w153" font-name="agaramondpro" symbolic="yes" bold="no" italic="no" font-size="11" font-color="#231f1f" rotation="0" angle="0" x="74.6628" y="297.406" base="307.493" width="15.818" height="13.981">and</TOKEN><TOKEN sid="p5_s2094" id="p5_w154" font-name="agaramondpro" symbolic="yes" bold="no" italic="no" font-size="11" font-color="#231f1f" rotation="0" angle="0" x="93.8688" y="297.406" base="307.493" width="45.243" height="13.981">Blakemore</TOKEN><TOKEN sid="p5_s2095" id="p5_w155" font-name="agaramondpro" symbolic="yes" bold="no" italic="no" font-size="11" font-color="#231f1f" rotation="0" angle="0" x="142.5" y="297.406" base="307.493" width="28.27" height="13.981">(2002,</TOKEN><TOKEN sid="p5_s2096" id="p5_w156" font-name="agaramondpro" symbolic="yes" bold="no" italic="no" font-size="11" font-color="#231f1f" rotation="0" angle="0" x="174.158" y="297.406" base="307.493" width="24.75" height="13.981">2008,</TOKEN><TOKEN sid="p5_s2097" id="p5_w157" font-name="agaramondpro" symbolic="yes" bold="no" italic="no" font-size="11" font-color="#231f1f" rotation="0" angle="0" x="202.296" y="297.406" base="307.493" width="24.75" height="13.981">2010,</TOKEN><TOKEN sid="p5_s2098" id="p5_w158" font-name="agaramondpro" symbolic="yes" bold="no" italic="no" font-size="11" font-color="#231f1f" rotation="0" angle="0" x="230.434" y="297.406" base="307.493" width="31.02" height="13.981">2000b)</TOKEN><TOKEN sid="p5_s2099" id="p5_w159" font-name="agaramondpro" symbolic="yes" bold="no" italic="no" font-size="11" font-color="#231f1f" rotation="0" angle="0" x="264.842" y="297.406" base="307.493" width="7.821" height="13.981">at</TOKEN><TOKEN sid="p5_s2100" id="p5_w160" font-name="agaramondpro" symbolic="yes" bold="no" italic="no" font-size="11" font-color="#231f1f" rotation="0" angle="0" x="276.051" y="297.406" base="307.493" width="24.222" height="13.981">genus</TOKEN><TOKEN sid="p5_s2101" id="p5_w161" font-name="agaramondpro" symbolic="yes" bold="no" italic="no" font-size="11" font-color="#231f1f" rotation="0" angle="0" x="303.661" y="297.406" base="307.493" width="15.818" height="13.981">and</TOKEN><TOKEN sid="p5_s2102" id="p5_w162" font-name="agaramondpro" symbolic="yes" bold="no" italic="no" font-size="11" font-color="#231f1f" rotation="0" angle="0" x="322.867" y="297.406" base="307.493" width="28.622" height="13.981">species</TOKEN><TOKEN sid="p5_s2103" id="p5_w163" font-name="agaramondpro" symbolic="yes" bold="no" italic="no" font-size="11" font-color="#231f1f" rotation="0" angle="0" x="354.866" y="297.406" base="307.493" width="25.135" height="13.981">levels.</TOKEN><TOKEN sid="p5_s2104" id="p5_w164" font-name="agaramondpro" symbolic="yes" bold="no" italic="no" font-size="11" font-color="#231f1f" rotation="0" angle="0" x="383.389" y="297.406" base="307.493" width="31.933" height="13.981">Discus-</TOKEN></TEXT><TEXT width="362.813" height="13.981" x="52.4428" y="310.606" id="p5_t19"><TOKEN sid="p5_s2105" id="p5_w165" font-name="agaramondpro" symbolic="yes" bold="no" italic="no" font-size="11" font-color="#231f1f" rotation="0" angle="0" x="52.4428" y="310.606" base="320.693" width="17.501" height="13.981">sion</TOKEN><TOKEN sid="p5_s2106" id="p5_w166" font-name="agaramondpro" symbolic="yes" bold="no" italic="no" font-size="11" font-color="#231f1f" rotation="0" angle="0" x="74.1568" y="310.606" base="320.693" width="6.38" height="13.981">is</TOKEN><TOKEN sid="p5_s2107" id="p5_w167" font-name="agaramondpro" symbolic="yes" bold="no" italic="no" font-size="11" font-color="#231f1f" rotation="0" angle="0" x="84.7498" y="310.606" base="320.693" width="36.993" height="13.981">confined</TOKEN><TOKEN sid="p5_s2108" id="p5_w168" font-name="agaramondpro" symbolic="yes" bold="no" italic="no" font-size="11" font-color="#231f1f" rotation="0" angle="0" x="125.956" y="310.606" base="320.693" width="8.723" height="13.981">to</TOKEN><TOKEN sid="p5_s2109" id="p5_w169" font-name="agaramondpro" symbolic="yes" bold="no" italic="no" font-size="11" font-color="#231f1f" rotation="0" angle="0" x="138.892" y="310.606" base="320.693" width="44.121" height="13.981">comments</TOKEN><TOKEN sid="p5_s2110" id="p5_w170" font-name="agaramondpro" symbolic="yes" bold="no" italic="no" font-size="11" font-color="#231f1f" rotation="0" angle="0" x="187.226" y="310.606" base="320.693" width="19.019" height="13.981">after</TOKEN><TOKEN sid="p5_s2111" id="p5_w171" font-name="agaramondpro" symbolic="yes" bold="no" italic="no" font-size="11" font-color="#231f1f" rotation="0" angle="0" x="210.458" y="310.606" base="320.693" width="28.622" height="13.981">species</TOKEN><TOKEN sid="p5_s2112" id="p5_w172" font-name="agaramondpro" symbolic="yes" bold="no" italic="no" font-size="11" font-color="#231f1f" rotation="0" angle="0" x="243.293" y="310.606" base="320.693" width="50.842" height="13.981">descriptions</TOKEN><TOKEN sid="p5_s2113" id="p5_w173" font-name="agaramondpro" symbolic="yes" bold="no" italic="no" font-size="11" font-color="#231f1f" rotation="0" angle="0" x="298.348" y="310.606" base="320.693" width="15.818" height="13.981">and</TOKEN><TOKEN sid="p5_s2114" id="p5_w174" font-name="agaramondpro" symbolic="yes" bold="no" italic="no" font-size="11" font-color="#231f1f" rotation="0" angle="0" x="318.379" y="310.606" base="320.693" width="34.584" height="13.981">endnote</TOKEN><TOKEN sid="p5_s2115" id="p5_w175" font-name="agaramondpro" symbolic="yes" bold="no" italic="no" font-size="11" font-color="#231f1f" rotation="0" angle="0" x="357.176" y="310.606" base="320.693" width="45.331" height="13.981">summaries</TOKEN><TOKEN sid="p5_s2116" id="p5_w176" font-name="agaramondpro" symbolic="yes" bold="no" italic="no" font-size="11" font-color="#231f1f" rotation="0" angle="0" x="406.72" y="310.606" base="320.693" width="8.536" height="13.981">of</TOKEN></TEXT><TEXT width="99.682" height="13.981" id="p5_t20" x="52.4428" y="323.806"><TOKEN sid="p5_s2117" id="p5_w177" font-name="agaramondpro" symbolic="yes" bold="no" italic="no" font-size="11" font-color="#231f1f" rotation="0" angle="0" x="52.4428" y="323.806" base="333.893" width="44.858" height="13.981">taxonomic</TOKEN><TOKEN sid="p5_s2118" id="p5_w178" font-name="agaramondpro" symbolic="yes" bold="no" italic="no" font-size="11" font-color="#231f1f" rotation="0" angle="0" x="100.051" y="323.806" base="333.893" width="52.074" height="13.981">conclusions.</TOKEN></TEXT><TEXT width="36.773" height="12.749" id="p5_t21" x="52.4428" y="368.906"><TOKEN sid="p5_s2119" id="p5_w179" font-name="gillsans" serif="yes" bold="yes" italic="no" font-size="11" font-color="#231f1f" rotation="0" angle="0" x="52.4428" y="368.906" base="379.125" width="36.773" height="12.749">Results</TOKEN></TEXT><TEXT width="110.715" height="13.211" id="p5_t22" x="52.4428" y="389.971"><TOKEN sid="p5_s2120" id="p5_w180" font-name="AGaramondPro" serif="yes" bold="yes" italic="no" font-size="11" font-color="#231f1f" rotation="0" angle="0" x="52.4428" y="389.971" base="399.86" width="20.02" height="13.211">New</TOKEN><TOKEN sid="p5_s2121" id="p5_w181" font-name="agaramondpro" serif="yes" bold="yes" italic="no" font-size="11" font-color="#231f1f" rotation="0" angle="0" x="75.1028" y="389.971" base="399.86" width="30.811" height="13.211">species</TOKEN><TOKEN sid="p5_s2122" id="p5_w182" font-name="agaramondpro" serif="yes" bold="yes" italic="no" font-size="11" font-color="#231f1f" rotation="0" angle="0" x="108.554" y="389.971" base="399.86" width="54.604" height="13.211">descriptions</TOKEN></TEXT><TEXT width="106.7" height="13.156" x="52.4428" y="416.404" id="p5_t23"><TOKEN sid="p5_s2123" id="p5_w183" href="http://zoobank.org/?lsid=urn:lsid:zoobank.org:act:F014AE5E-D434-4119-B949-E5AB86DB1E4E" font-name="AGaramondPro" serif="yes" bold="yes" italic="yes" font-size="11" font-color="#231f1f" rotation="0" angle="0" x="52.4428" y="416.459" base="426.293" width="52.789" height="13.145">Aporodrilus</TOKEN><TOKEN sid="p5_s2124" id="p5_w184" href="http://zoobank.org/?lsid=urn:lsid:zoobank.org:act:F014AE5E-D434-4119-B949-E5AB86DB1E4E" font-name="agaramondpro" serif="yes" bold="yes" italic="yes" font-size="11" font-color="#231f1f" rotation="0" angle="0" x="107.872" y="416.459" base="426.293" width="24.2" height="13.145">aotea</TOKEN><TOKEN sid="p5_s2125" id="p5_w185" href="http://zoobank.org/?lsid=urn:lsid:zoobank.org:act:F014AE5E-D434-4119-B949-E5AB86DB1E4E" font-name="agaramondpro" serif="yes" bold="yes" italic="no" font-size="11" font-color="#231f1f" rotation="0" angle="0" x="134.822" y="416.404" base="426.293" width="12.771" height="13.211">sp.</TOKEN><TOKEN sid="p5_s2126" id="p5_w186" href="http://zoobank.org/?lsid=urn:lsid:zoobank.org:act:F014AE5E-D434-4119-B949-E5AB86DB1E4E" font-name="agaramondpro" serif="yes" bold="yes" italic="no" font-size="11" font-color="#231f1f" rotation="0" angle="0" x="150.233" y="416.404" base="426.293" width="8.91" height="13.211">n.</TOKEN></TEXT><TEXT width="312.873" height="13.981" x="52.4428" y="428.207" id="p5_t24"><TOKEN sid="p5_s2127" id="p5_w187" href="http://zoobank.org/?lsid=urn:lsid:zoobank.org:act:F014AE5E-D434-4119-B949-E5AB86DB1E4E" font-name="agaramondpro" symbolic="yes" bold="no" italic="no" font-size="11" font-color="#1b2853" rotation="0" angle="0" x="52.4428" y="428.207" base="438.294" width="312.873" height="13.981">urn:lsid:zoobank.org:act:F014AE5E-D434-4119-B949-E5AB86DB1E4E</TOKEN></TEXT><TEXT width="188.199" height="13.981" x="52.4428" y="440.208" id="p5_t25"><TOKEN sid="p5_s2128" id="p5_w188" href="http://zoobank.org/?lsid=urn:lsid:zoobank.org:act:F014AE5E-D434-4119-B949-E5AB86DB1E4E" font-name="agaramondpro" symbolic="yes" bold="no" italic="no" font-size="11" font-color="#1b2853" rotation="0" angle="0" x="52.4428" y="440.208" base="450.295" width="188.199" height="13.981">http://species-id.net/wiki/Aporodrilus_aotea</TOKEN></TEXT><TEXT width="24.277" height="13.981" id="p5_t26" x="52.4428" y="453.408"><TOKEN sid="p5_s2129" id="p5_w189" href="http://species-id.net/wiki/Aporodrilus_aotea" font-name="agaramondpro" symbolic="yes" bold="no" italic="no" font-size="11" font-color="#231f1f" rotation="0" angle="0" x="52.4428" y="453.408" base="463.495" width="16.027" height="13.981">Fig.</TOKEN><TOKEN sid="p5_s2130" id="p5_w190" href="http://species-id.net/wiki/Aporodrilus_aotea" font-name="agaramondpro" symbolic="yes" bold="no" italic="no" font-size="11" font-color="#231f1f" rotation="0" angle="0" x="71.2198" y="453.408" base="463.495" width="5.5" height="13.981">1</TOKEN></TEXT><TEXT width="362.802" height="13.783" x="52.4428" y="482.206" id="p5_t27"><TOKEN sid="p5_s2131" id="p5_w191" font-name="agaramondpro" serif="yes" bold="yes" italic="no" font-size="11" font-color="#231f1f" rotation="0" angle="0" x="52.4428" y="482.404" base="492.293" width="38.06" height="13.211">Material</TOKEN><TOKEN sid="p5_s2132" id="p5_w192" font-name="agaramondpro" serif="yes" bold="yes" italic="no" font-size="11" font-color="#231f1f" rotation="0" angle="0" x="94.6168" y="482.404" base="492.293" width="47.817" height="13.211">Examined.</TOKEN><TOKEN sid="p5_s2133" id="p5_w193" font-name="agaramondpro" symbolic="yes" bold="no" italic="no" font-size="11" font-color="#231f1f" rotation="0" angle="0" x="146.713" y="482.206" base="492.293" width="40.205" height="13.981">Holotype</TOKEN><TOKEN sid="p5_s2134" id="p5_w194" font-name="agaramondpro" symbolic="yes" bold="no" italic="no" font-size="11" font-color="#231f1f" rotation="0" angle="0" x="191.197" y="482.206" base="492.293" width="40.524" height="13.981">Auckland</TOKEN><TOKEN sid="p5_s2135" id="p5_w195" font-name="agaramondpro" symbolic="yes" bold="no" italic="no" font-size="11" font-color="#231f1f" rotation="0" angle="0" x="236" y="482.206" base="492.293" width="40.216" height="13.981">Museum;</TOKEN><TOKEN sid="p5_s2136" id="p5_w196" font-name="agaramondpro" symbolic="yes" bold="no" italic="no" font-size="11" font-color="#231f1f" rotation="0" angle="0" x="280.495" y="482.206" base="492.293" width="32.549" height="13.981">AMNZ</TOKEN><TOKEN sid="p5_s2137" id="p5_w197" font-name="agaramondpro" symbolic="yes" bold="no" italic="no" font-size="11" font-color="#231f1f" rotation="0" angle="0" x="317.323" y="482.206" base="492.293" width="24.75" height="13.981">5254.</TOKEN><TOKEN sid="p5_s2138" id="p5_w198" font-name="agaramondpro" symbolic="yes" bold="no" italic="no" font-size="11" font-color="#231f1f" rotation="0" angle="0" x="346.352" y="482.206" base="492.293" width="25.828" height="13.981">Single</TOKEN><TOKEN sid="p5_s2139" id="p5_w199" font-name="agaramondpro" symbolic="yes" bold="no" italic="no" font-size="11" font-color="#231f1f" rotation="0" angle="0" x="376.459" y="482.206" base="492.293" width="38.786" height="13.981">complete</TOKEN></TEXT><TEXT width="362.791" height="13.981" x="52.4428" y="495.406" id="p5_t28"><TOKEN sid="p5_s2140" id="p5_w200" font-name="agaramondpro" symbolic="yes" bold="no" italic="no" font-size="11" font-color="#231f1f" rotation="0" angle="0" x="52.4428" y="495.406" base="505.493" width="42.251" height="13.981">specimen,</TOKEN><TOKEN sid="p5_s2141" id="p5_w201" font-name="agaramondpro" symbolic="yes" bold="no" italic="no" font-size="11" font-color="#231f1f" rotation="0" angle="0" x="97.7848" y="495.406" base="505.493" width="18.249" height="13.981">now</TOKEN><TOKEN sid="p5_s2142" id="p5_w202" font-name="agaramondpro" symbolic="yes" bold="no" italic="no" font-size="11" font-color="#231f1f" rotation="0" angle="0" x="119.125" y="495.406" base="505.493" width="40.37" height="13.981">dissected,</TOKEN><TOKEN sid="p5_s2143" id="p5_w203" font-name="agaramondpro" symbolic="yes" bold="no" italic="no" font-size="11" font-color="#231f1f" rotation="0" angle="0" x="162.586" y="495.406" base="505.493" width="20.779" height="13.981">from</TOKEN><TOKEN sid="p5_s2144" id="p5_w204" font-name="agaramondpro" symbolic="yes" bold="no" italic="no" font-size="11" font-color="#231f1f" rotation="0" angle="0" x="186.456" y="495.406" base="505.493" width="19.965" height="13.981">New</TOKEN><TOKEN sid="p5_s2145" id="p5_w205" font-name="agaramondpro" symbolic="yes" bold="no" italic="no" font-size="11" font-color="#231f1f" rotation="0" angle="0" x="209.512" y="495.406" base="505.493" width="37.07" height="13.981">Zealand,</TOKEN><TOKEN sid="p5_s2146" id="p5_w206" font-name="agaramondpro" symbolic="yes" bold="no" italic="no" font-size="11" font-color="#231f1f" rotation="0" angle="0" x="249.673" y="495.406" base="505.493" width="23.672" height="13.981">Great</TOKEN><TOKEN sid="p5_s2147" id="p5_w207" font-name="agaramondpro" symbolic="yes" bold="no" italic="no" font-size="11" font-color="#231f1f" rotation="0" angle="0" x="276.436" y="495.406" base="505.493" width="29.106" height="13.981">Barrier</TOKEN><TOKEN sid="p5_s2148" id="p5_w208" font-name="agaramondpro" symbolic="yes" bold="no" italic="no" font-size="11" font-color="#231f1f" rotation="0" angle="0" x="308.633" y="495.406" base="505.493" width="28.358" height="13.981">Island,</TOKEN><TOKEN sid="p5_s2149" id="p5_w209" font-name="agaramondpro" symbolic="yes" bold="no" italic="no" font-size="11" font-color="#231f1f" rotation="0" angle="0" x="340.082" y="495.406" base="505.493" width="22.737" height="13.981">Little</TOKEN><TOKEN sid="p5_s2150" id="p5_w210" font-name="agaramondpro" symbolic="yes" bold="no" italic="no" font-size="11" font-color="#231f1f" rotation="0" angle="0" x="365.745" y="495.406" base="505.493" width="29.469" height="13.981">Windy</TOKEN><TOKEN sid="p5_s2151" id="p5_w211" font-name="agaramondpro" symbolic="yes" bold="no" italic="no" font-size="11" font-color="#231f1f" rotation="0" angle="0" x="398.305" y="495.406" base="505.493" width="16.929" height="13.981">Hill</TOKEN></TEXT><TEXT width="362.791" height="13.981" x="52.4428" y="508.606" id="p5_t29"><TOKEN sid="p5_s2152" id="p5_w212" font-name="agaramondpro" symbolic="yes" bold="no" italic="no" font-size="11" font-color="#231f1f" rotation="0" angle="0" x="52.4428" y="508.606" base="518.693" width="15.114" height="13.981">(ca.</TOKEN><TOKEN sid="p5_s2153" id="p5_w213" font-name="agaramondpro" symbolic="yes" bold="no" italic="no" font-size="11" font-color="#231f1f" rotation="0" angle="0" x="70.9448" y="508.606" base="518.693" width="36.036" height="13.981">36°10'S,</TOKEN><TOKEN sid="p5_s2154" id="p5_w214" font-name="agaramondpro" symbolic="yes" bold="no" italic="no" font-size="11" font-color="#231f1f" rotation="0" angle="0" x="110.369" y="508.606" base="518.693" width="46.101" height="13.981">175°23'E).</TOKEN><TOKEN sid="p5_s2155" id="p5_w215" font-name="agaramondpro" symbolic="yes" bold="no" italic="no" font-size="11" font-color="#231f1f" rotation="0" angle="0" x="159.858" y="508.606" base="518.693" width="21.186" height="13.981">Coll:</TOKEN><TOKEN sid="p5_s2156" id="p5_w216" font-name="agaramondpro" symbolic="yes" bold="no" italic="no" font-size="11" font-color="#231f1f" rotation="0" angle="0" x="184.432" y="508.606" base="518.693" width="46.541" height="13.981">2.IX.2001,</TOKEN><TOKEN sid="p5_s2157" id="p5_w217" font-name="agaramondpro" symbolic="yes" bold="no" italic="no" font-size="11" font-color="#231f1f" rotation="0" angle="0" x="234.361" y="508.606" base="518.693" width="18.535" height="13.981">J.W.</TOKEN><TOKEN sid="p5_s2158" id="p5_w218" font-name="agaramondpro" symbolic="yes" bold="no" italic="no" font-size="11" font-color="#231f1f" rotation="0" angle="0" x="256.284" y="508.606" base="518.693" width="22.055" height="13.981">Early</TOKEN><TOKEN sid="p5_s2159" id="p5_w219" font-name="agaramondpro" symbolic="yes" bold="no" italic="no" font-size="11" font-color="#231f1f" rotation="0" angle="0" x="281.727" y="508.606" base="518.693" width="8.998" height="13.981">&amp;</TOKEN><TOKEN sid="p5_s2160" id="p5_w220" font-name="agaramondpro" symbolic="yes" bold="no" italic="no" font-size="11" font-color="#231f1f" rotation="0" angle="0" x="294.113" y="508.606" base="518.693" width="16.973" height="13.981">R.F.</TOKEN><TOKEN sid="p5_s2161" id="p5_w221" font-name="agaramondpro" symbolic="yes" bold="no" italic="no" font-size="11" font-color="#231f1f" rotation="0" angle="0" x="314.474" y="508.606" base="518.693" width="33.352" height="13.981">Gilbert.</TOKEN><TOKEN sid="p5_s2162" id="p5_w222" font-name="agaramondpro" symbolic="yes" bold="no" italic="no" font-size="11" font-color="#231f1f" rotation="0" angle="0" x="351.214" y="508.606" base="518.693" width="30.47" height="13.981">“Under</TOKEN><TOKEN sid="p5_s2163" id="p5_w223" font-name="agaramondpro" symbolic="yes" bold="no" italic="yes" font-size="11" font-color="#231f1f" rotation="0" angle="0" x="385.072" y="508.606" base="518.693" width="16.797" height="13.805">rock</TOKEN><TOKEN sid="p5_s2164" id="p5_w224" font-name="agaramondpro" symbolic="yes" bold="no" italic="yes" font-size="11" font-color="#231f1f" rotation="0" angle="0" x="405.257" y="508.606" base="518.693" width="9.977" height="13.805">on</TOKEN></TEXT><TEXT width="362.78" height="13.981" x="52.4428" y="521.806" id="p5_t30"><TOKEN sid="p5_s2165" id="p5_w225" font-name="agaramondpro" symbolic="yes" bold="no" italic="yes" font-size="11" font-color="#231f1f" rotation="0" angle="0" x="52.4428" y="521.806" base="531.893" width="20.68" height="13.805">forest</TOKEN><TOKEN sid="p5_s2166" id="p5_w226" font-name="agaramondpro" symbolic="yes" bold="no" italic="yes" font-size="11" font-color="#231f1f" rotation="0" angle="0" x="75.5428" y="521.806" base="531.893" width="20.152" height="13.805">floor.</TOKEN><TOKEN sid="p5_s2167" id="p5_w227" font-name="agaramondpro" symbolic="yes" bold="no" italic="yes" font-size="11" font-color="#231f1f" rotation="0" angle="0" x="98.1148" y="521.806" base="531.893" width="40.7" height="13.805">L11002”.</TOKEN><TOKEN sid="p5_s2168" id="p5_w228" font-name="agaramondpro" symbolic="yes" bold="no" italic="no" font-size="11" font-color="#231f1f" rotation="0" angle="0" x="141.235" y="521.806" base="531.893" width="38.126" height="13.981">“W-025”</TOKEN><TOKEN sid="p5_s2169" id="p5_w229" font-name="agaramondpro" symbolic="yes" bold="no" italic="no" font-size="11" font-color="#231f1f" rotation="0" angle="0" x="181.781" y="521.806" base="531.893" width="11.121" height="13.981">on</TOKEN><TOKEN sid="p5_s2170" id="p5_w230" font-name="agaramondpro" symbolic="yes" bold="no" italic="no" font-size="11" font-color="#231f1f" rotation="0" angle="0" x="195.322" y="521.806" base="531.893" width="13.893" height="13.981">lid.</TOKEN><TOKEN sid="p5_s2171" id="p5_w231" font-name="agaramondpro" symbolic="yes" bold="no" italic="no" font-size="11" font-color="#231f1f" rotation="0" angle="0" x="211.635" y="521.806" base="531.893" width="27.17" height="13.981">(Small</TOKEN><TOKEN sid="p5_s2172" id="p5_w232" font-name="agaramondpro" symbolic="yes" bold="no" italic="no" font-size="11" font-color="#231f1f" rotation="0" angle="0" x="241.225" y="521.806" base="531.893" width="23.298" height="13.981">tissue</TOKEN><TOKEN sid="p5_s2173" id="p5_w233" font-name="agaramondpro" symbolic="yes" bold="no" italic="no" font-size="11" font-color="#231f1f" rotation="0" angle="0" x="266.943" y="521.806" base="531.893" width="29.304" height="13.981">sample</TOKEN><TOKEN sid="p5_s2174" id="p5_w234" font-name="agaramondpro" symbolic="yes" bold="no" italic="no" font-size="11" font-color="#231f1f" rotation="0" angle="0" x="298.667" y="521.806" base="531.893" width="15.257" height="13.981">was</TOKEN><TOKEN sid="p5_s2175" id="p5_w235" font-name="agaramondpro" symbolic="yes" bold="no" italic="no" font-size="11" font-color="#231f1f" rotation="0" angle="0" x="316.344" y="521.806" base="531.893" width="23.254" height="13.981">taken</TOKEN><TOKEN sid="p5_s2176" id="p5_w236" font-name="agaramondpro" symbolic="yes" bold="no" italic="no" font-size="11" font-color="#231f1f" rotation="0" angle="0" x="342.018" y="521.806" base="531.893" width="12.188" height="13.981">for</TOKEN><TOKEN sid="p5_s2177" id="p5_w237" font-name="agaramondpro" symbolic="yes" bold="no" italic="no" font-size="11" font-color="#231f1f" rotation="0" angle="0" x="356.626" y="521.806" base="531.893" width="24.046" height="13.981">DNA</TOKEN><TOKEN sid="p5_s2178" id="p5_w238" font-name="agaramondpro" symbolic="yes" bold="no" italic="no" font-size="11" font-color="#231f1f" rotation="0" angle="0" x="383.092" y="521.806" base="531.893" width="32.131" height="13.981">analysis</TOKEN></TEXT><TEXT width="63.536" height="13.981" x="52.4428" y="535.006" id="p5_t31"><TOKEN sid="p5_s2179" id="p5_w239" font-name="agaramondpro" symbolic="yes" bold="no" italic="no" font-size="11" font-color="#231f1f" rotation="0" angle="0" x="52.4428" y="535.006" base="545.093" width="3.52" height="13.981">-</TOKEN><TOKEN sid="p5_s2180" id="p5_w240" font-name="agaramondpro" symbolic="yes" bold="no" italic="no" font-size="11" font-color="#231f1f" rotation="0" angle="0" x="58.7128" y="535.006" base="545.093" width="19.701" height="13.981">code</TOKEN><TOKEN sid="p5_s2181" id="p5_w241" font-name="agaramondpro" symbolic="yes" bold="no" italic="no" font-size="11" font-color="#231f1f" rotation="0" angle="0" x="81.1638" y="535.006" base="545.093" width="34.815" height="13.981">RJB09).</TOKEN></TEXT><TEXT width="345.862" height="13.783" x="69.4488" y="548.206" id="p5_t32"><TOKEN sid="p5_s2182" id="p5_w242" font-name="agaramondpro" serif="yes" bold="yes" italic="no" font-size="11" font-color="#231f1f" rotation="0" angle="0" x="69.4488" y="548.404" base="558.293" width="50.666" height="13.211">Etymology.</TOKEN><TOKEN sid="p5_s2183" id="p5_w243" font-name="agaramondpro" symbolic="yes" bold="no" italic="no" font-size="11" font-color="#231f1f" rotation="0" angle="0" x="123.811" y="548.206" base="558.293" width="21.428" height="13.981">After</TOKEN><TOKEN sid="p5_s2184" id="p5_w244" font-name="agaramondpro" symbolic="yes" bold="no" italic="no" font-size="11" font-color="#231f1f" rotation="0" angle="0" x="148.935" y="548.206" base="558.293" width="26.169" height="13.981">Maori</TOKEN><TOKEN sid="p5_s2185" id="p5_w245" font-name="agaramondpro" symbolic="yes" bold="no" italic="no" font-size="11" font-color="#231f1f" rotation="0" angle="0" x="178.8" y="548.206" base="558.293" width="23.232" height="13.981">name</TOKEN><TOKEN sid="p5_s2186" id="p5_w246" font-name="agaramondpro" symbolic="yes" bold="no" italic="no" font-size="11" font-color="#231f1f" rotation="0" angle="0" x="205.728" y="548.206" base="558.293" width="12.188" height="13.981">for</TOKEN><TOKEN sid="p5_s2187" id="p5_w247" font-name="agaramondpro" symbolic="yes" bold="no" italic="no" font-size="11" font-color="#231f1f" rotation="0" angle="0" x="221.612" y="548.206" base="558.293" width="23.672" height="13.981">Great</TOKEN><TOKEN sid="p5_s2188" id="p5_w248" font-name="agaramondpro" symbolic="yes" bold="no" italic="no" font-size="11" font-color="#231f1f" rotation="0" angle="0" x="248.98" y="548.206" base="558.293" width="29.106" height="13.981">Barrier</TOKEN><TOKEN sid="p5_s2189" id="p5_w249" font-name="agaramondpro" symbolic="yes" bold="no" italic="no" font-size="11" font-color="#231f1f" rotation="0" angle="0" x="281.771" y="548.206" base="558.293" width="28.358" height="13.981">Island;</TOKEN><TOKEN sid="p5_s2190" id="p5_w250" font-name="agaramondpro" symbolic="yes" bold="no" italic="yes" font-size="11" font-color="#231f1f" rotation="0" angle="0" x="313.825" y="548.206" base="558.293" width="46.97" height="13.805">Aporodrilus</TOKEN><TOKEN sid="p5_s2191" id="p5_w251" font-name="agaramondpro" symbolic="yes" bold="no" italic="no" font-size="11" font-color="#231f1f" rotation="0" angle="0" x="364.491" y="548.206" base="558.293" width="6.38" height="13.981">is</TOKEN><TOKEN sid="p5_s2192" id="p5_w252" font-name="agaramondpro" symbolic="yes" bold="no" italic="no" font-size="11" font-color="#231f1f" rotation="0" angle="0" x="374.567" y="548.206" base="558.293" width="29.051" height="13.981">treated</TOKEN><TOKEN sid="p5_s2193" id="p5_w253" font-name="agaramondpro" symbolic="yes" bold="no" italic="no" font-size="11" font-color="#231f1f" rotation="0" angle="0" x="407.314" y="548.206" base="558.293" width="7.997" height="13.981">as</TOKEN></TEXT><TEXT width="314.215" height="13.981" x="52.4428" y="561.406" id="p5_t33"><TOKEN sid="p5_s2194" id="p5_w254" font-name="agaramondpro" symbolic="yes" bold="no" italic="no" font-size="11" font-color="#231f1f" rotation="0" angle="0" x="52.4428" y="561.406" base="571.493" width="42.361" height="13.981">masculine</TOKEN><TOKEN sid="p5_s2195" id="p5_w255" font-name="agaramondpro" symbolic="yes" bold="no" italic="no" font-size="11" font-color="#231f1f" rotation="0" angle="0" x="97.5538" y="561.406" base="571.493" width="14.509" height="13.981">but</TOKEN><TOKEN sid="p5_s2196" id="p5_w256" font-name="agaramondpro" symbolic="yes" bold="no" italic="no" font-size="11" font-color="#231f1f" rotation="0" angle="0" x="114.813" y="561.406" base="571.493" width="15.422" height="13.981">this</TOKEN><TOKEN sid="p5_s2197" id="p5_w257" font-name="agaramondpro" symbolic="yes" bold="no" italic="no" font-size="11" font-color="#231f1f" rotation="0" angle="0" x="132.985" y="561.406" base="571.493" width="21.494" height="13.981">place</TOKEN><TOKEN sid="p5_s2198" id="p5_w258" font-name="agaramondpro" symbolic="yes" bold="no" italic="no" font-size="11" font-color="#231f1f" rotation="0" angle="0" x="157.229" y="561.406" base="571.493" width="23.232" height="13.981">name</TOKEN><TOKEN sid="p5_s2199" id="p5_w259" font-name="agaramondpro" symbolic="yes" bold="no" italic="no" font-size="11" font-color="#231f1f" rotation="0" angle="0" x="183.211" y="561.406" base="571.493" width="33.154" height="13.981">remains</TOKEN><TOKEN sid="p5_s2200" id="p5_w260" font-name="agaramondpro" symbolic="yes" bold="no" italic="no" font-size="11" font-color="#231f1f" rotation="0" angle="0" x="219.115" y="561.406" base="571.493" width="42.823" height="13.981">genderless</TOKEN><TOKEN sid="p5_s2201" id="p5_w261" font-name="agaramondpro" symbolic="yes" bold="no" italic="no" font-size="11" font-color="#231f1f" rotation="0" angle="0" x="264.688" y="561.406" base="571.493" width="7.997" height="13.981">as</TOKEN><TOKEN sid="p5_s2202" id="p5_w262" font-name="agaramondpro" symbolic="yes" bold="no" italic="no" font-size="11" font-color="#231f1f" rotation="0" angle="0" x="275.435" y="561.406" base="571.493" width="4.444" height="13.981">a</TOKEN><TOKEN sid="p5_s2203" id="p5_w263" font-name="agaramondpro" symbolic="yes" bold="no" italic="no" font-size="11" font-color="#231f1f" rotation="0" angle="0" x="282.629" y="561.406" base="571.493" width="22.528" height="13.981">noun</TOKEN><TOKEN sid="p5_s2204" id="p5_w264" font-name="agaramondpro" symbolic="yes" bold="no" italic="no" font-size="11" font-color="#231f1f" rotation="0" angle="0" x="307.907" y="561.406" base="571.493" width="8.602" height="13.981">in</TOKEN><TOKEN sid="p5_s2205" id="p5_w265" font-name="agaramondpro" symbolic="yes" bold="no" italic="no" font-size="11" font-color="#231f1f" rotation="0" angle="0" x="319.259" y="561.406" base="571.493" width="47.399" height="13.981">apposition.</TOKEN></TEXT><TEXT width="345.829" height="13.783" x="69.4488" y="574.606" id="p5_t34"><TOKEN sid="p5_s2206" id="p5_w266" font-name="agaramondpro" serif="yes" bold="yes" italic="no" font-size="11" font-color="#231f1f" rotation="0" angle="0" x="69.4488" y="574.804" base="584.693" width="47.487" height="13.211">Diagnosis.</TOKEN><TOKEN sid="p5_s2207" id="p5_w267" font-name="agaramondpro" symbolic="yes" bold="no" italic="yes" font-size="11" font-color="#231f1f" rotation="0" angle="0" x="120.06" y="574.606" base="584.693" width="46.97" height="13.805">Aporodrilus</TOKEN><TOKEN sid="p5_s2208" id="p5_w268" font-name="agaramondpro" symbolic="yes" bold="no" italic="no" font-size="11" font-color="#231f1f" rotation="0" angle="0" x="170.154" y="574.606" base="584.693" width="28.369" height="13.981">having</TOKEN><TOKEN sid="p5_s2209" id="p5_w269" font-name="agaramondpro" symbolic="yes" bold="no" italic="no" font-size="11" font-color="#231f1f" rotation="0" angle="0" x="201.647" y="574.606" base="584.693" width="55.198" height="13.981">spermathecal</TOKEN><TOKEN sid="p5_s2210" id="p5_w270" font-name="agaramondpro" symbolic="yes" bold="no" italic="no" font-size="11" font-color="#231f1f" rotation="0" angle="0" x="259.969" y="574.606" base="584.693" width="22.374" height="13.981">pores</TOKEN><TOKEN sid="p5_s2211" id="p5_w271" font-name="agaramondpro" symbolic="yes" bold="no" italic="no" font-size="11" font-color="#231f1f" rotation="0" angle="0" x="285.467" y="574.606" base="584.693" width="26.345" height="13.981">paired</TOKEN><TOKEN sid="p5_s2212" id="p5_w272" font-name="agaramondpro" symbolic="yes" bold="no" italic="no" font-size="11" font-color="#231f1f" rotation="0" angle="0" x="314.936" y="574.606" base="584.693" width="49.676" height="13.981">segmentally</TOKEN><TOKEN sid="p5_s2213" id="p5_w273" font-name="agaramondpro" symbolic="yes" bold="no" italic="no" font-size="11" font-color="#231f1f" rotation="0" angle="0" x="367.736" y="574.606" base="584.693" width="8.602" height="13.981">in</TOKEN><TOKEN sid="p5_s2214" id="p5_w274" font-name="agaramondpro" symbolic="yes" bold="no" italic="no" font-size="11" font-color="#231f1f" rotation="0" angle="0" x="379.462" y="574.606" base="584.693" width="8.25" height="13.981">6,</TOKEN><TOKEN sid="p5_s2215" id="p5_w275" font-name="agaramondpro" symbolic="yes" bold="no" italic="no" font-size="11" font-color="#231f1f" rotation="0" angle="0" x="390.836" y="574.606" base="584.693" width="5.5" height="13.981">7</TOKEN><TOKEN sid="p5_s2216" id="p5_w276" font-name="agaramondpro" symbolic="yes" bold="no" italic="no" font-size="11" font-color="#231f1f" rotation="0" angle="0" x="399.46" y="574.606" base="584.693" width="15.818" height="13.981">and</TOKEN></TEXT><TEXT width="362.791" height="13.981" x="52.4428" y="587.806" id="p5_t35"><TOKEN sid="p5_s2217" id="p5_w277" font-name="agaramondpro" symbolic="yes" bold="no" italic="no" font-size="11" font-color="#231f1f" rotation="0" angle="0" x="52.4428" y="587.806" base="597.893" width="8.25" height="13.981">8;</TOKEN><TOKEN sid="p5_s2218" id="p5_w278" font-name="agaramondpro" symbolic="yes" bold="no" italic="no" font-size="11" font-color="#231f1f" rotation="0" angle="0" x="63.9048" y="587.806" base="597.893" width="38.214" height="13.981">holandry</TOKEN><TOKEN sid="p5_s2219" id="p5_w279" font-name="agaramondpro" symbolic="yes" bold="no" italic="no" font-size="11" font-color="#231f1f" rotation="0" angle="0" x="105.331" y="587.806" base="597.893" width="19.129" height="13.981">with</TOKEN><TOKEN sid="p5_s2220" id="p5_w280" font-name="agaramondpro" symbolic="yes" bold="no" italic="no" font-size="11" font-color="#231f1f" rotation="0" angle="0" x="127.672" y="587.806" base="597.893" width="32.329" height="13.981">seminal</TOKEN><TOKEN sid="p5_s2221" id="p5_w281" font-name="agaramondpro" symbolic="yes" bold="no" italic="no" font-size="11" font-color="#231f1f" rotation="0" angle="0" x="163.213" y="587.806" base="597.893" width="30.448" height="13.981">vesicles</TOKEN><TOKEN sid="p5_s2222" id="p5_w282" font-name="agaramondpro" symbolic="yes" bold="no" italic="no" font-size="11" font-color="#231f1f" rotation="0" angle="0" x="196.873" y="587.806" base="597.893" width="8.602" height="13.981">in</TOKEN><TOKEN sid="p5_s2223" id="p5_w283" font-name="agaramondpro" symbolic="yes" bold="no" italic="no" font-size="11" font-color="#231f1f" rotation="0" angle="0" x="208.687" y="587.806" base="597.893" width="5.5" height="13.981">9</TOKEN><TOKEN sid="p5_s2224" id="p5_w284" font-name="agaramondpro" symbolic="yes" bold="no" italic="no" font-size="11" font-color="#231f1f" rotation="0" angle="0" x="217.399" y="587.806" base="597.893" width="15.818" height="13.981">and</TOKEN><TOKEN sid="p5_s2225" id="p5_w285" font-name="agaramondpro" symbolic="yes" bold="no" italic="no" font-size="11" font-color="#231f1f" rotation="0" angle="0" x="236.429" y="587.806" base="597.893" width="13.75" height="13.981">12;</TOKEN><TOKEN sid="p5_s2226" id="p5_w286" font-name="agaramondpro" symbolic="yes" bold="no" italic="no" font-size="11" font-color="#231f1f" rotation="0" angle="0" x="253.391" y="587.806" base="597.893" width="50.71" height="13.981">oesophageal</TOKEN><TOKEN sid="p5_s2227" id="p5_w287" font-name="agaramondpro" symbolic="yes" bold="no" italic="no" font-size="11" font-color="#231f1f" rotation="0" angle="0" x="307.313" y="587.806" base="597.893" width="26.994" height="13.981">glands</TOKEN><TOKEN sid="p5_s2228" id="p5_w288" font-name="agaramondpro" symbolic="yes" bold="no" italic="no" font-size="11" font-color="#231f1f" rotation="0" angle="0" x="337.519" y="587.806" base="597.893" width="32.439" height="13.981">annular</TOKEN><TOKEN sid="p5_s2229" id="p5_w289" font-name="agaramondpro" symbolic="yes" bold="no" italic="no" font-size="11" font-color="#231f1f" rotation="0" angle="0" x="373.17" y="587.806" base="597.893" width="8.602" height="13.981">in</TOKEN><TOKEN sid="p5_s2230" id="p5_w290" font-name="agaramondpro" symbolic="yes" bold="no" italic="no" font-size="11" font-color="#231f1f" rotation="0" angle="0" x="384.984" y="587.806" base="597.893" width="30.25" height="13.981">10–14;</TOKEN></TEXT><TEXT width="330.759" height="13.981" id="p5_t36" x="52.4428" y="601.006"><TOKEN sid="p5_s2231" id="p5_w291" font-name="agaramondpro" symbolic="yes" bold="no" italic="no" font-size="11" font-color="#231f1f" rotation="0" angle="0" x="52.4428" y="601.006" base="611.093" width="20.075" height="13.981">large</TOKEN><TOKEN sid="p5_s2232" id="p5_w292" font-name="agaramondpro" symbolic="yes" bold="no" italic="no" font-size="11" font-color="#231f1f" rotation="0" angle="0" x="75.2678" y="601.006" base="611.093" width="28.402" height="13.981">genital</TOKEN><TOKEN sid="p5_s2233" id="p5_w293" font-name="agaramondpro" symbolic="yes" bold="no" italic="no" font-size="11" font-color="#231f1f" rotation="0" angle="0" x="106.42" y="601.006" base="611.093" width="39.05" height="13.981">markings</TOKEN><TOKEN sid="p5_s2234" id="p5_w294" font-name="agaramondpro" symbolic="yes" bold="no" italic="no" font-size="11" font-color="#231f1f" rotation="0" angle="0" x="148.22" y="601.006" base="611.093" width="26.345" height="13.981">paired</TOKEN><TOKEN sid="p5_s2235" id="p5_w295" font-name="agaramondpro" symbolic="yes" bold="no" italic="no" font-size="11" font-color="#231f1f" rotation="0" angle="0" x="177.315" y="601.006" base="611.093" width="8.602" height="13.981">in</TOKEN><TOKEN sid="p5_s2236" id="p5_w296" font-name="agaramondpro" symbolic="yes" bold="no" italic="no" font-size="11" font-color="#231f1f" rotation="0" angle="0" x="188.667" y="601.006" base="611.093" width="25.597" height="13.981">17/18</TOKEN><TOKEN sid="p5_s2237" id="p5_w297" font-name="agaramondpro" symbolic="yes" bold="no" italic="no" font-size="11" font-color="#231f1f" rotation="0" angle="0" x="217.014" y="601.006" base="611.093" width="15.818" height="13.981">and</TOKEN><TOKEN sid="p5_s2238" id="p5_w298" font-name="agaramondpro" symbolic="yes" bold="no" italic="no" font-size="11" font-color="#231f1f" rotation="0" angle="0" x="235.582" y="601.006" base="611.093" width="25.597" height="13.981">18/19</TOKEN><TOKEN sid="p5_s2239" id="p5_w299" font-name="agaramondpro" symbolic="yes" bold="no" italic="no" font-size="11" font-color="#231f1f" rotation="0" angle="0" x="263.929" y="601.006" base="611.093" width="11.121" height="13.981">on</TOKEN><TOKEN sid="p5_s2240" id="p5_w300" font-name="agaramondpro" symbolic="yes" bold="no" italic="no" font-size="11" font-color="#231f1f" rotation="0" angle="0" x="277.8" y="601.006" base="611.093" width="24.233" height="13.981">either</TOKEN><TOKEN sid="p5_s2241" id="p5_w301" font-name="agaramondpro" symbolic="yes" bold="no" italic="no" font-size="11" font-color="#231f1f" rotation="0" angle="0" x="304.783" y="601.006" base="611.093" width="16.335" height="13.981">side</TOKEN><TOKEN sid="p5_s2242" id="p5_w302" font-name="agaramondpro" symbolic="yes" bold="no" italic="no" font-size="11" font-color="#231f1f" rotation="0" angle="0" x="323.868" y="601.006" base="611.093" width="8.536" height="13.981">of</TOKEN><TOKEN sid="p5_s2243" id="p5_w303" font-name="agaramondpro" symbolic="yes" bold="no" italic="no" font-size="11" font-color="#231f1f" rotation="0" angle="0" x="335.154" y="601.006" base="611.093" width="20.174" height="13.981">male</TOKEN><TOKEN sid="p5_s2244" id="p5_w304" font-name="agaramondpro" symbolic="yes" bold="no" italic="no" font-size="11" font-color="#231f1f" rotation="0" angle="0" x="358.078" y="601.006" base="611.093" width="25.124" height="13.981">pores.</TOKEN></TEXT><xi:include xmlns:xi="http://www.w3.org/2001/XInclude" href="2354-G-3-layout.xml_data/image-5.vec"/></PAGE>
